[{"Name":"test1","Weight":100,"Remark":"","WaveList":[[{"Position":{"X":15,"Y":12},"Size":{"X":14,"Y":16},"SpecialMarkType":1,"DelayTime":0,"MarkList":[]},{"Position":{"X":23,"Y":-7},"Size":{"X":30,"Y":12},"SpecialMarkType":0,"DelayTime":0,"MarkList":[{"Id":"weapon0001","Weight":100,"Attr":{"CurrAmmon":"30","ResidueAmmo":"210"},"Altitude":8,"VerticalSpeed":0}]},{"Position":{"X":8,"Y":32},"Size":{"X":16,"Y":16},"SpecialMarkType":0,"DelayTime":0,"MarkList":[{"Id":"weapon0002","Weight":100,"Attr":{"CurrAmmon":"7","ResidueAmmo":"70"},"Altitude":8,"VerticalSpeed":0}]},{"Position":{"X":-40,"Y":7},"Size":{"X":16,"Y":16},"SpecialMarkType":0,"DelayTime":0,"MarkList":[{"Id":"weapon0004","Weight":100,"Attr":{"CurrAmmon":"180","ResidueAmmo":"90"},"Altitude":8,"VerticalSpeed":0}]},{"Position":{"X":-63,"Y":-18},"Size":{"X":16,"Y":16},"SpecialMarkType":0,"DelayTime":0,"MarkList":[{"Id":"weapon0005","Weight":100,"Attr":{"CurrAmmon":"10","ResidueAmmo":"40"},"Altitude":8,"VerticalSpeed":0}]},{"Position":{"X":-31,"Y":-16},"Size":{"X":16,"Y":16},"SpecialMarkType":0,"DelayTime":0,"MarkList":[{"Id":"weapon0003","Weight":100,"Attr":{"CurrAmmon":"12","ResidueAmmo":"90"},"Altitude":8,"VerticalSpeed":0}]},{"Position":{"X":-54,"Y":33},"Size":{"X":16,"Y":16},"SpecialMarkType":0,"DelayTime":0,"MarkList":[{"Id":"weapon0006","Weight":100,"Attr":{"CurrAmmon":"20","ResidueAmmo":"300"},"Altitude":8,"VerticalSpeed":0}]},{"Position":{"X":2,"Y":-25},"Size":{"X":16,"Y":16},"SpecialMarkType":0,"DelayTime":0,"MarkList":[{"Id":"weapon0007","Weight":100,"Attr":{"CurrAmmon":"60","ResidueAmmo":"300"},"Altitude":8,"VerticalSpeed":0}]},{"Position":{"X":-76,"Y":21},"Size":{"X":16,"Y":16},"SpecialMarkType":0,"DelayTime":0,"MarkList":[{"Id":"weapon0008","Weight":100,"Attr":{"CurrAmmon":"10","ResidueAmmo":"120"},"Altitude":8,"VerticalSpeed":0}]},{"Position":{"X":-82,"Y":53},"Size":{"X":16,"Y":16},"SpecialMarkType":0,"DelayTime":0,"MarkList":[{"Id":"weapon0009","Weight":100,"Attr":{"CurrAmmon":"1","ResidueAmmo":"25"},"Altitude":8,"VerticalSpeed":0}]},{"Position":{"X":58,"Y":4},"Size":{"X":16,"Y":16},"SpecialMarkType":0,"DelayTime":0,"MarkList":[{"Id":"prop0011","Weight":100,"Attr":null,"Altitude":8,"VerticalSpeed":0}]},{"Position":{"X":45,"Y":55},"Size":{"X":16,"Y":16},"SpecialMarkType":0,"DelayTime":0,"MarkList":[{"Id":"prop0012","Weight":100,"Attr":null,"Altitude":8,"VerticalSpeed":0}]},{"Position":{"X":-90,"Y":-26},"Size":{"X":13,"Y":16},"SpecialMarkType":0,"DelayTime":0,"MarkList":[{"Id":"prop0013","Weight":100,"Attr":null,"Altitude":8,"VerticalSpeed":0}]},{"Position":{"X":-91,"Y":-6},"Size":{"X":14,"Y":13},"SpecialMarkType":0,"DelayTime":0,"MarkList":[{"Id":"prop0014","Weight":100,"Attr":null,"Altitude":8,"VerticalSpeed":0}]}],[{"Position":{"X":72,"Y":62},"Size":{"X":16,"Y":16},"SpecialMarkType":0,"DelayTime":0,"MarkList":[{"Id":"prop0003","Weight":100,"Attr":null,"Altitude":8,"VerticalSpeed":0}]},{"Position":{"X":67,"Y":28},"Size":{"X":16,"Y":17},"SpecialMarkType":0,"DelayTime":0.5,"MarkList":[{"Id":"prop5000","Weight":100,"Attr":null,"Altitude":8,"VerticalSpeed":0}]},{"Position":{"X":60,"Y":-19},"Size":{"X":16,"Y":16},"SpecialMarkType":0,"DelayTime":1,"MarkList":[{"Id":"prop5001","Weight":100,"Attr":null,"Altitude":8,"VerticalSpeed":0}]},{"Position":{"X":37,"Y":24},"Size":{"X":16,"Y":16},"SpecialMarkType":0,"DelayTime":1.5,"MarkList":[{"Id":"prop0002","Weight":100,"Attr":null,"Altitude":8,"VerticalSpeed":0}]},{"Position":{"X":-11,"Y":6},"Size":{"X":18,"Y":16},"SpecialMarkType":0,"DelayTime":0,"MarkList":[{"Id":"prop0010","Weight":100,"Attr":null,"Altitude":8,"VerticalSpeed":0}]},{"Position":{"X":-21,"Y":32},"Size":{"X":16,"Y":16},"SpecialMarkType":0,"DelayTime":0,"MarkList":[{"Id":"prop0010","Weight":100,"Attr":null,"Altitude":8,"VerticalSpeed":0}]}]]},{"Name":"test2","Weight":100,"Remark":"","WaveList":[[{"Position":{"X":0,"Y":0},"Size":{"X":0,"Y":0},"SpecialMarkType":1,"DelayTime":0,"MarkList":[]}]]}]