{
  "Position": {
    "X": -1,
    "Y": -1
  },
  "Size": {
    "X": 19,
    "Y": 12
  },
  "DoorAreaInfos": [],
  "NavigationList": [
    {
      "Type": 0,
      "Points": [
        {
          "X": 8,
          "Y": 8
        },
        {
          "X": 40,
          "Y": 8
        },
        {
          "X": 40,
          "Y": 120
        },
        {
          "X": 120,
          "Y": 120
        },
        {
          "X": 120,
          "Y": 8
        },
        {
          "X": 264,
          "Y": 8
        },
        {
          "X": 264,
          "Y": 152
        },
        {
          "X": 232,
          "Y": 152
        },
        {
          "X": 232,
          "Y": 24
        },
        {
          "X": 152,
          "Y": 24
        },
        {
          "X": 152,
          "Y": 152
        },
        {
          "X": 8,
          "Y": 152
        }
      ]
    }
  ],
  "GroupName": "testGroup",
  "RoomType": 0,
  "FileName": "Room2"
}